bin/boost_atomic.dll
bin/boost_filesystem.dll
bin/boost_python310.dll
bin/boost_serialization.dll
bin/lanelet2_core.dll
bin/lanelet2_io.dll
bin/lanelet2_matching.dll
bin/lanelet2_projection.dll
bin/lanelet2_routing.dll
bin/lanelet2_traffic_rules.dll
bin/python310.dll
lanelet2/__init__.py
lanelet2/core.cp310-win_amd64.pyd
lanelet2/geometry.cp310-win_amd64.pyd
lanelet2/io.cp310-win_amd64.pyd
lanelet2/matching.cp310-win_amd64.pyd
lanelet2/projection.cp310-win_amd64.pyd
lanelet2/routing.cp310-win_amd64.pyd
lanelet2/traffic_rules.cp310-win_amd64.pyd
lanelet2x-1.2.1.dist-info/METADATA
lanelet2x-1.2.1.dist-info/WHEEL
lanelet2x-1.2.1.dist-info/entry_points.txt
lanelet2x-1.2.1.dist-info/licenses/LICENSE
lanelet2x-1.2.1.dist-info/licenses/CODEOWNERS
lanelet2x-1.2.1.dist-info/RECORD
