Metadata-Version: 2.1
Name: lanelet2x
Version: 1.2.1
Summary: Your favorite map handling framework for automated driving, now standalone and with cross-platform support.
Keywords: python lanelet2
Author-Email: Fabian Poggenhans <fabian.poggenhans@kit.edu>, Fabian Immel <fabian.immel@kit.edu>
Maintainer-Email: Vincent Wu <zhengyu.wu21@imperial.ac.uk>
License: Copyright 2018 FZI Forschungszentrum Informatik
Classifier: Programming Language :: Python
Classifier: Programming Language :: Python :: 3
Classifier: Programming Language :: Python :: 3.9
Classifier: Programming Language :: Python :: 3.10
Classifier: Programming Language :: Python :: 3.11
Classifier: Programming Language :: Python :: 3.12
Classifier: License :: OSI Approved :: BSD License
Classifier: Operating System :: MacOS
Classifier: Operating System :: Microsoft :: Windows
Classifier: Operating System :: POSIX :: Linux
Requires-Python: >=3.9
Provides-Extra: pytest
Requires-Dist: pytest; extra == "pytest"
License-File: LICENSE
License-File: CODEOWNERS
